deweypy/__init__.py
deweypy/__main__.py
deweypy/app.py
deweypy/auth.py
deweypy/context.py
deweypy/display.py
deweypy/download/__init__.py
deweypy/download/asynchronous.py
deweypy/download/errors.py
deweypy/download/settings.py
deweypy/download/speed_testing.py
deweypy/download/speedy.py
deweypy/download/synchronous.py
deweypy/download/types.py
deweypy/main.py
deweypy/py.typed
deweypy-0.7.0.dist-info/WHEEL
deweypy-0.7.0.dist-info/entry_points.txt
deweypy-0.7.0.dist-info/METADATA
deweypy-0.7.0.dist-info/RECORD
