Metadata-Version: 2.3
Name: deweypy
Version: 0.7.0
Summary: A Python client for Dewey Data (https://deweydata.io/).
Requires-Dist: aiofiles>=25.1.0
Requires-Dist: aiopath>=0.7.7
Requires-Dist: anyio>=4.12.0
Requires-Dist: async-property>=0.2.2
Requires-Dist: attrs>=25.4.0
Requires-Dist: culsans>=0.10.0
Requires-Dist: httpx-aiohttp>=0.1.9
Requires-Dist: httpx[http2]>=0.28.1
Requires-Dist: ipywidgets>=8.1.8
Requires-Dist: python-slugify>=8.0.4
Requires-Dist: rich>=14.2.0
Requires-Dist: shellingham>=1.5.4
Requires-Dist: typer>=0.20.0
Requires-Python: >=3.12, <3.14
